tensorio_bundler/__init__.py
tensorio_bundler/bundler.py
tensorio_bundler/rest.py
tensorio_bundler/test_bundler.py
tensorio_bundler/test_rest.py
tensorio_bundler-0.3.2.dist-info/LICENSE
tensorio_bundler-0.3.2.dist-info/METADATA
tensorio_bundler-0.3.2.dist-info/WHEEL
tensorio_bundler-0.3.2.dist-info/top_level.txt
tensorio_bundler-0.3.2.dist-info/RECORD
