Metadata-Version: 2.1
Name: tensorio-bundler
Version: 0.3.2
Summary: Bundle models for use with TensorIO
Home-page: https://github.com/doc-ai/tensorio-bundler
Author: Doc.ai
Author-email: neeraj@doc.ai
License: Apache License 2.0
Platform: UNKNOWN
Classifier: Programming Language :: Python :: 3
Classifier: Operating System :: OS Independent
Classifier: Topic :: Software Development :: Libraries
Requires-Dist: absl-py (~=0.7.1)
Requires-Dist: astor (~=0.7.1)
Requires-Dist: astroid (~=2.1.0)
Requires-Dist: bleach (~=3.1.0)
Requires-Dist: certifi (~=2018.11.29)
Requires-Dist: chardet (~=3.0.4)
Requires-Dist: docutils (~=0.14)
Requires-Dist: falcon (~=1.4.1)
Requires-Dist: gast (~=0.2.2)
Requires-Dist: grpcio (~=1.18.0)
Requires-Dist: gunicorn (~=19.9.0)
Requires-Dist: h5py (~=2.9.0)
Requires-Dist: idna (~=2.8)
Requires-Dist: isort (~=4.3.20)
Requires-Dist: Keras-Applications (~=1.0.7)
Requires-Dist: Keras-Preprocessing (~=1.0.9)
Requires-Dist: lazy-object-proxy (~=1.4.3)
Requires-Dist: Markdown (~=3.0.1)
Requires-Dist: mccabe (~=0.6.1)
Requires-Dist: numpy (~=1.16.4)
Requires-Dist: pkginfo (~=1.5.0.1)
Requires-Dist: protobuf (~=3.6.1)
Requires-Dist: Pygments (~=2.3.1)
Requires-Dist: pylint (~=2.2.3)
Requires-Dist: python-mimeparse (~=1.6.0)
Requires-Dist: readme-renderer (~=24.0)
Requires-Dist: requests (~=2.21.0)
Requires-Dist: requests-toolbelt (~=0.9.1)
Requires-Dist: six (~=1.12.0)
Requires-Dist: tensorboard (~=1.14.0)
Requires-Dist: tensorflow (~=1.14.0)
Requires-Dist: termcolor (~=1.1.0)
Requires-Dist: tqdm (~=4.30.0)
Requires-Dist: twine (~=1.12.1)
Requires-Dist: typed-ast (~=1.1.2)
Requires-Dist: urllib3 (~=1.24.3)
Requires-Dist: webencodings (~=0.5.1)
Requires-Dist: websocket-client (~=0.54.0)
Requires-Dist: Werkzeug (~=0.14.1)
Requires-Dist: wrapt (~=1.11.1)
